threedi_mi_utils/__init__.py
threedi_mi_utils/news/__init__.py
threedi_mi_utils/news/news_injector.py
threedi_mi_utils/tests/__init__.py
threedi_mi_utils/tests/conftest.py
threedi_mi_utils/tests/news_test.py
threedi_mi_utils/tests/working_dir_test.py
threedi_mi_utils/working_dir/__init__.py
threedi_mi_utils/working_dir/working_dir.py
threedi_mi_utils-0.1.13.dist-info/licenses/LICENSE
threedi_mi_utils-0.1.13.dist-info/METADATA
threedi_mi_utils-0.1.13.dist-info/WHEEL
threedi_mi_utils-0.1.13.dist-info/top_level.txt
threedi_mi_utils-0.1.13.dist-info/RECORD
